video_speed_mcp/__init__.py
video_speed_mcp/main.py
mcpcn_video_speed_mcp-0.1.8.dist-info/METADATA
mcpcn_video_speed_mcp-0.1.8.dist-info/WHEEL
mcpcn_video_speed_mcp-0.1.8.dist-info/entry_points.txt
mcpcn_video_speed_mcp-0.1.8.dist-info/RECORD
