Metadata-Version: 2.4
Name: mcpcn-video-speed-mcp
Version: 0.1.8
Summary: MCP server for changing video playback speed with proper audio sync
Author-email: Your Name <your.email@example.com>
License: MIT
Keywords: fast-forward,ffmpeg,mcp,slow-motion,speed,video
Classifier: Development Status :: 4 - Beta
Classifier: Intended Audience :: Developers
Classifier: License :: OSI Approved :: MIT License
Classifier: Programming Language :: Python :: 3
Classifier: Programming Language :: Python :: 3.12
Classifier: Topic :: Multimedia :: Video
Requires-Python: >=3.12
Requires-Dist: ffmpeg-python>=0.2.0
Requires-Dist: mcp[cli]>=1.9.0
